MANIFEST.in
README.md
pyproject.toml
setup.py
torchcast/__init__.py
torchcast.egg-info/PKG-INFO
torchcast.egg-info/SOURCES.txt
torchcast.egg-info/dependency_links.txt
torchcast.egg-info/top_level.txt
torchcast/csrc/file_readers.cpp
torchcast/csrc/ts_reader.cpp
torchcast/csrc/ts_reader.h
torchcast/csrc/tsf_reader.cpp
torchcast/csrc/tsf_reader.h
torchcast/csrc/utils.cpp
torchcast/csrc/utils.h
torchcast/data/__init__.py
torchcast/data/h5_dataset.py
torchcast/data/samplers.py
torchcast/data/series_dataset.py
torchcast/data/tensor_dataset.py
torchcast/data/transforms.py
torchcast/data/utils.py
torchcast/datasets/__init__.py
torchcast/datasets/air_quality.py
torchcast/datasets/electricity.py
torchcast/datasets/ett.py
torchcast/datasets/exchange_rate.py
torchcast/datasets/illness.py
torchcast/datasets/largest.py
torchcast/datasets/monash.py
torchcast/datasets/tfb.py
torchcast/datasets/tfb.txt
torchcast/datasets/traffic.py
torchcast/datasets/ucr.py
torchcast/datasets/utils.py
torchcast/datasets/weather.py
torchcast/nn/__init__.py
torchcast/nn/criteria.py
torchcast/nn/layers.py
torchcast/nn/models.py
torchcast/nn/transformers.py
torchcast/utils/__init__.py
torchcast/utils/_shaping.py
torchcast/utils/autocov.py
torchcast/utils/scoring.py
torchcast/utils/spectral.py