Metadata-Version: 2.2
Name: torchcast
Version: 0.1
Summary: A simple PyTorch library for time series analysis
Author: Mark Lowell
Author-email: Mark Lowell <MarkLowell@theorem-engine.org>
Project-URL: Homepage, https://github.com/TheoremEngine/torchcast
Project-URL: Issues, https://github.com/TheoremEngine/torchcast/issues
Classifier: Programming Language :: Python :: 3
Classifier: Operating System :: OS Independent
Classifier: License :: OSI Approved :: MIT License
Dynamic: author
